cvasl_gui/__init__.py
cvasl_gui/app.py
cvasl_gui/assets/custom.css
cvasl_gui/assets/style.css
cvasl_gui/components/data_table.py
cvasl_gui/components/directory_input.py
cvasl_gui/components/feature_compare.py
cvasl_gui/components/feature_compare2.py
cvasl_gui/components/plots/box_plot.py
cvasl_gui/components/plots/box_plot2.py
cvasl_gui/components/plots/scatter_plot.py
cvasl_gui/components/plots/scatter_plot2.py
cvasl_gui/components/plots/violin_plot.py
cvasl_gui/components/plots/violin_plot2.py
cvasl_gui/data_store.py
cvasl_gui/index.py
cvasl_gui/jobs/harmonization_job.py
cvasl_gui/jobs/prediction_job.py
cvasl_gui/tabs/harmonization.py
cvasl_gui/tabs/job_list.py
cvasl_gui/tabs/parameters.py
cvasl_gui/tabs/prediction.py
cvasl_gui-0.2.3.dist-info/METADATA
cvasl_gui-0.2.3.dist-info/WHEEL
cvasl_gui-0.2.3.dist-info/entry_points.txt
cvasl_gui-0.2.3.dist-info/licenses/LICENSE
cvasl_gui-0.2.3.dist-info/RECORD
