Metadata-Version: 2.4
Name: cvasl-gui
Version: 0.2.3
Summary: A GUI for the cvasl package
License: Apache 2.0
License-File: LICENSE
Author: Peter Kok
Author-email: p.kok@esciencecenter.nl
Requires-Python: >=3.10,<3.14
Classifier: License :: Other/Proprietary License
Classifier: Programming Language :: Python :: 3
Classifier: Programming Language :: Python :: 3.10
Classifier: Programming Language :: Python :: 3.11
Classifier: Programming Language :: Python :: 3.12
Classifier: Programming Language :: Python :: 3.13
Requires-Dist: cvasl (==0.2.1)
Requires-Dist: dash (>=2.18.2,<3.0.0)
Requires-Dist: dash-bootstrap-components (==1.7.1)
Requires-Dist: pandas (>=2.2.3,<3.0.0)
Requires-Dist: python-dotenv (>=1.0.1,<2.0.0)
Requires-Dist: waitress (>=3.0.2,<4.0.0)
